{"Data":"2024-10-24T19:07:00-03:00","sudesteECentroOeste":{"geracao":{"total":39769.582,"hidraulica":23452.3066,"termica":8081.39941,"eolica":8.0,"nuclear":2008.51929,"solar":2.0854094,"itaipu50HzBrasil":2223.5,"itaipu60Hz":3993.76953},"cargaVerificada":51790.53,"importacao":12020.9492,"exportacao":0.0},"sul":{"geracao":{"total":15644.0068,"hidraulica":12811.1973,"termica":1516.61121,"eolica":1313.26526,"nuclear":0.0,"solar":2.9333334},"cargaVerificada":16556.209,"importacao":1698.51135,"exportacao":786.3092},"nordeste":{"geracao":{"total":25306.8,"hidraulica":4500.588,"termica":1495.42151,"eolica":19310.1641,"nuclear":0.0,"solar":0.626874864},"cargaVerificada":14895.9336,"importacao":0.0,"exportacao":10407.082},"norte":{"geracao":{"total":9301.107,"hidraulica":6182.41943,"termica":2721.86768,"eolica":394.8871,"nuclear":0.0,"solar":1.93333328},"cargaVerificada":8473.549,"importacao":0.0,"exportacao":827.5586},"internacional":{"argentina":-1199.90369,"paraguai":0.0,"uruguai":-498.5227},"intercambio":{"internacional_sul":1698.51135,"sul_sudeste":786.3092,"sudeste_nordeste":-1656.58472,"sudeste_norteFic":-9578.056,"norte_norteFic":827.5586,"norteFic_nordeste":-8750.497}}