{"Data":"2024-09-07T07:56:00-03:00","sudesteECentroOeste":{"geracao":{"total":32952.4531,"hidraulica":12025.2139,"termica":7595.864,"eolica":6.0,"nuclear":2007.92664,"solar":7160.60352,"itaipu50HzBrasil":1616.43,"itaipu60Hz":2540.41382},"cargaVerificada":38606.5,"importacao":9721.125,"exportacao":4067.078},"sul":{"geracao":{"total":6675.82373,"hidraulica":4127.897,"termica":910.9894,"eolica":288.204071,"nuclear":0.0,"solar":1348.73328},"cargaVerificada":10743.1318,"importacao":4067.308,"exportacao":0.0},"nordeste":{"geracao":{"total":22033.0547,"hidraulica":2184.3562,"termica":311.4364,"eolica":14256.1465,"nuclear":0.0,"solar":5281.116},"cargaVerificada":11407.0068,"importacao":0.0,"exportacao":10624.8936},"norte":{"geracao":{"total":6325.15039,"hidraulica":2315.42188,"termica":2921.44482,"eolica":404.137268,"nuclear":0.0,"solar":684.146667},"cargaVerificada":7228.919,"importacao":903.768555,"exportacao":0.0},"internacional":{"argentina":0.008882198,"paraguai":0.0,"uruguai":-0.239},"intercambio":{"internacional_sul":0.230145767,"sul_sudeste":-4067.078,"sudeste_nordeste":-2190.14844,"sudeste_norteFic":-7530.97656,"norte_norteFic":-903.768555,"norteFic_nordeste":-8434.745}}