{"Data":"2025-01-29T19:23:00-03:00","sudesteECentroOeste":{"geracao":{"total":50947.0078,"hidraulica":36718.2969,"termica":2413.48633,"eolica":6.0,"nuclear":1996.40381,"solar":14.3249626,"itaipu50HzBrasil":3024.56982,"itaipu60Hz":6773.92773},"cargaVerificada":54326.3828,"importacao":7532.81836,"exportacao":4153.445},"sul":{"geracao":{"total":13620.2148,"hidraulica":12118.8994,"termica":859.4843,"eolica":637.20105,"nuclear":0.0,"solar":4.63},"cargaVerificada":17213.7676,"importacao":4153.445,"exportacao":559.892},"nordeste":{"geracao":{"total":12729.0732,"hidraulica":5541.318,"termica":376.291534,"eolica":6812.53,"nuclear":0.0,"solar":-1.06570446},"cargaVerificada":14432.8818,"importacao":3556.47119,"exportacao":1853.04431},"norte":{"geracao":{"total":17533.01,"hidraulica":15641.4287,"termica":1711.3219,"eolica":180.025467,"nuclear":0.0,"solar":0.233333334},"cargaVerificada":8296.765,"importacao":0.0,"exportacao":9236.245},"internacional":{"argentina":263.003571,"paraguai":0.0,"uruguai":296.9143},"intercambio":{"internacional_sul":-559.892,"sul_sudeste":-4153.445,"sudeste_nordeste":-1853.04431,"sudeste_norteFic":-5679.774,"norte_norteFic":9236.245,"norteFic_nordeste":3556.47119}}