{"Data":"2024-06-07T15:57:00-03:00","sudesteECentroOeste":{"geracao":{"total":37013.9,"hidraulica":19197.3516,"termica":4499.764,"eolica":3.0,"nuclear":2001.55811,"solar":5706.19629,"itaipu50HzBrasil":1171.2699,"itaipu60Hz":4434.76025},"cargaVerificada":45978.1055,"importacao":8964.207,"exportacao":0.0},"sul":{"geracao":{"total":16339.9541,"hidraulica":14354.3438,"termica":763.153259,"eolica":73.09409,"nuclear":0.0,"solar":1149.36328},"cargaVerificada":14931.58,"importacao":0.0,"exportacao":1408.374},"nordeste":{"geracao":{"total":17712.4023,"hidraulica":4472.23926,"termica":378.235718,"eolica":9810.809,"nuclear":0.0,"solar":3051.119},"cargaVerificada":13625.5068,"importacao":0.0,"exportacao":4087.85864},"norte":{"geracao":{"total":12948.6045,"hidraulica":10778.8281,"termica":1520.44324,"eolica":148.2216,"nuclear":0.0,"solar":501.1111},"cargaVerificada":8489.075,"importacao":0.0,"exportacao":4459.5293},"internacional":{"argentina":991.684937,"paraguai":0.0,"uruguai":-0.128233343},"intercambio":{"internacional_sul":-991.5549,"sul_sudeste":416.819153,"sudeste_nordeste":-1009.12329,"sudeste_norteFic":-7538.26465,"norte_norteFic":4459.5293,"norteFic_nordeste":-3078.73535}}