{"Data":"2025-04-15T05:25:00-03:00","sudesteECentroOeste":{"geracao":{"total":36067.1367,"hidraulica":25389.959,"termica":3455.364,"eolica":6.0,"nuclear":1351.672,"solar":4.7285285,"itaipu50HzBrasil":1516.78,"itaipu60Hz":4342.63232},"cargaVerificada":39625.1,"importacao":9637.504,"exportacao":6079.53857},"sul":{"geracao":{"total":4882.8833,"hidraulica":3117.0686,"termica":1209.64783,"eolica":556.1669,"nuclear":0.0,"solar":0.0},"cargaVerificada":10963.1475,"importacao":6080.264,"exportacao":0.0},"nordeste":{"geracao":{"total":10476.7275,"hidraulica":2887.05737,"termica":300.422546,"eolica":7231.684,"nuclear":0.0,"solar":57.56345},"cargaVerificada":13291.4092,"importacao":3679.03613,"exportacao":864.373535},"norte":{"geracao":{"total":20141.7,"hidraulica":17810.9375,"termica":2203.47339,"eolica":127.287895,"nuclear":0.0,"solar":0.0},"cargaVerificada":7689.532,"importacao":0.0,"exportacao":12452.167},"internacional":{"argentina":-0.0104192914,"paraguai":0.0,"uruguai":-0.717},"intercambio":{"internacional_sul":0.7256615,"sul_sudeste":-6079.53857,"sudeste_nordeste":-864.373535,"sudeste_norteFic":-8773.131,"norte_norteFic":12452.167,"norteFic_nordeste":3679.03613}}