{"Data":"2025-05-31T22:51:00-03:00","sudesteECentroOeste":{"geracao":{"total":33680.1758,"hidraulica":23416.0684,"termica":4358.147,"eolica":3.0,"nuclear":1362.79077,"solar":6.502201,"itaipu50HzBrasil":1433.43494,"itaipu60Hz":3100.234},"cargaVerificada":39317.8867,"importacao":13070.3838,"exportacao":7432.67432},"sul":{"geracao":{"total":3558.25171,"hidraulica":1775.68054,"termica":1410.23218,"eolica":371.338959,"nuclear":0.0,"solar":1.0},"cargaVerificada":10991.9092,"importacao":7433.65771,"exportacao":0.0},"nordeste":{"geracao":{"total":23387.54,"hidraulica":4755.93,"termica":342.763245,"eolica":18292.5547,"nuclear":0.0,"solar":-3.70860481},"cargaVerificada":13861.8545,"importacao":0.0,"exportacao":9525.1875},"norte":{"geracao":{"total":12080.5273,"hidraulica":9446.764,"termica":2269.32031,"eolica":364.443817,"nuclear":0.0,"solar":0.0},"cargaVerificada":8535.331,"importacao":0.0,"exportacao":3545.19678},"internacional":{"argentina":0.01121806,"paraguai":0.0,"uruguai":-0.924},"intercambio":{"internacional_sul":0.9834045,"sul_sudeste":-7432.67432,"sudeste_nordeste":-6327.281,"sudeste_norteFic":-6743.103,"norte_norteFic":3545.19678,"norteFic_nordeste":-3197.90625}}