{"Data":"2026-03-02T05:34:00-03:00","sudesteECentroOeste":{"geracao":{"total":42497.71,"hidraulica":34035.15,"termica":3998.36328,"eolica":6.0625,"nuclear":468.215332,"solar":57.8229179,"itaipu50HzBrasil":307.56,"itaipu60Hz":3624.53857},"cargaVerificada":39482.2148,"importacao":6244.90234,"exportacao":9260.398},"sul":{"geracao":{"total":3803.45532,"hidraulica":2034.83752,"termica":755.936768,"eolica":1011.02094,"nuclear":0.0,"solar":1.66000009},"cargaVerificada":13064.0742,"importacao":9260.619,"exportacao":0.0},"nordeste":{"geracao":{"total":9720.485,"hidraulica":2739.40015,"termica":1696.46826,"eolica":5183.455,"nuclear":0.0,"solar":101.161957},"cargaVerificada":12455.0518,"importacao":3617.64941,"exportacao":883.036865},"norte":{"geracao":{"total":16967.2168,"hidraulica":15158.8184,"termica":1752.56555,"eolica":54.3477325,"nuclear":0.0,"solar":1.485},"cargaVerificada":7987.70166,"importacao":0.0,"exportacao":8979.515},"internacional":{"argentina":-0.000763867865,"paraguai":0.0,"uruguai":-0.2},"intercambio":{"internacional_sul":0.220762163,"sul_sudeste":-9260.398,"sudeste_nordeste":-883.036865,"sudeste_norteFic":-5361.865,"norte_norteFic":8979.515,"norteFic_nordeste":3617.64941}}