{"Data":"2024-06-14T14:51:00-03:00","sudesteECentroOeste":{"geracao":{"total":35595.0078,"hidraulica":16078.3984,"termica":4748.40869,"eolica":2.0,"nuclear":2002.77234,"solar":8529.354,"itaipu50HzBrasil":1173.7,"itaipu60Hz":3060.37524},"cargaVerificada":46240.47,"importacao":10645.4609,"exportacao":0.0},"sul":{"geracao":{"total":18203.2129,"hidraulica":14092.1025,"termica":1023.01465,"eolica":899.958252,"nuclear":0.0,"solar":2188.13818},"cargaVerificada":15436.99,"importacao":0.0,"exportacao":2766.22266},"nordeste":{"geracao":{"total":21118.5352,"hidraulica":3083.97583,"termica":411.017242,"eolica":12430.6045,"nuclear":0.0,"solar":5192.9375},"cargaVerificada":13296.6533,"importacao":0.0,"exportacao":7822.696},"norte":{"geracao":{"total":8566.5625,"hidraulica":6651.65234,"termica":932.3859,"eolica":92.56791,"nuclear":0.0,"solar":889.956665},"cargaVerificada":8509.905,"importacao":0.0,"exportacao":56.6572266},"internacional":{"argentina":0.00676617445,"paraguai":0.0,"uruguai":0.124391668},"intercambio":{"internacional_sul":-0.114720128,"sul_sudeste":2766.108,"sudeste_nordeste":-1482.33508,"sudeste_norteFic":-6397.018,"norte_norteFic":56.6572266,"norteFic_nordeste":-6340.361}}