{"Data":"2025-03-31T20:42:00-03:00","sudesteECentroOeste":{"geracao":{"total":46590.0352,"hidraulica":32804.582,"termica":4828.75,"eolica":2.0,"nuclear":1919.25574,"solar":8.377135,"itaipu50HzBrasil":2014.81,"itaipu60Hz":5012.261},"cargaVerificada":54019.46,"importacao":14303.34,"exportacao":6873.91553},"sul":{"geracao":{"total":10092.2109,"hidraulica":8091.87061,"termica":949.462036,"eolica":1049.87781,"nuclear":0.0,"solar":1.0},"cargaVerificada":16966.3418,"importacao":6874.13135,"exportacao":0.0},"nordeste":{"geracao":{"total":21136.0371,"hidraulica":5898.287,"termica":324.271942,"eolica":14915.1,"nuclear":0.0,"solar":-1.62139463},"cargaVerificada":14837.6348,"importacao":0.0,"exportacao":6298.217},"norte":{"geracao":{"total":16232.0439,"hidraulica":15166.7441,"termica":998.329651,"eolica":66.97063,"nuclear":0.0,"solar":0.0},"cargaVerificada":8226.921,"importacao":0.0,"exportacao":8005.12354},"internacional":{"argentina":0.00687991362,"paraguai":0.0,"uruguai":-0.389},"intercambio":{"internacional_sul":0.215583086,"sul_sudeste":-6873.91553,"sudeste_nordeste":-6027.67139,"sudeste_norteFic":-8275.669,"norte_norteFic":8005.12354,"norteFic_nordeste":-270.5454}}