{"Data":"2024-07-06T21:53:00-03:00","sudesteECentroOeste":{"geracao":{"total":35861.15,"hidraulica":23449.0762,"termica":4199.84961,"eolica":10.0,"nuclear":2002.93579,"solar":8.555218,"itaipu50HzBrasil":2784.22974,"itaipu60Hz":3406.50049},"cargaVerificada":41079.74,"importacao":5218.59,"exportacao":0.0},"sul":{"geracao":{"total":16062.78,"hidraulica":14626.1836,"termica":1170.36829,"eolica":265.228821,"nuclear":0.0,"solar":1.0},"cargaVerificada":12883.2725,"importacao":0.0,"exportacao":3179.50781},"nordeste":{"geracao":{"total":18178.2344,"hidraulica":6283.37646,"termica":336.449677,"eolica":11558.0156,"nuclear":0.0,"solar":0.392169446},"cargaVerificada":13062.8848,"importacao":0.0,"exportacao":5118.01563},"norte":{"geracao":{"total":6570.90039,"hidraulica":4630.67871,"termica":1806.98633,"eolica":133.2356,"nuclear":0.0,"solar":0.0},"cargaVerificada":8051.06055,"importacao":1480.16016,"exportacao":0.0},"internacional":{"argentina":1788.84766,"paraguai":0.0,"uruguai":-0.272833347},"intercambio":{"internacional_sul":-1598.7738,"sul_sudeste":1580.734,"sudeste_nordeste":-435.485474,"sudeste_norteFic":-3202.37036,"norte_norteFic":-1480.16016,"norteFic_nordeste":-4682.53027}}