{"Data":"2025-01-23T13:33:00-03:00","sudesteECentroOeste":{"geracao":{"total":55980.05,"hidraulica":28781.71,"termica":3451.87866,"eolica":5.0,"nuclear":1361.17419,"solar":14221.6611,"itaipu50HzBrasil":2726.25,"itaipu60Hz":5432.37549},"cargaVerificada":58193.76,"importacao":6467.448,"exportacao":4253.737},"sul":{"geracao":{"total":16399.084,"hidraulica":10890.8135,"termica":738.5822,"eolica":281.148041,"nuclear":0.0,"solar":4488.54},"cargaVerificada":20653.3184,"importacao":4254.235,"exportacao":0.0},"nordeste":{"geracao":{"total":14880.9639,"hidraulica":2887.56055,"termica":367.2399,"eolica":3254.27563,"nuclear":0.0,"solar":8371.888},"cargaVerificada":13327.4629,"importacao":280.621582,"exportacao":1834.63855},"norte":{"geracao":{"total":12589.84,"hidraulica":9926.502,"termica":1399.731,"eolica":94.45013,"nuclear":0.0,"solar":1169.15662},"cargaVerificada":7676.40869,"importacao":0.0,"exportacao":4913.431},"internacional":{"argentina":0.00864358153,"paraguai":0.0,"uruguai":-0.5092083},"intercambio":{"internacional_sul":0.497990847,"sul_sudeste":-4253.737,"sudeste_nordeste":-1834.63855,"sudeste_norteFic":-4632.80957,"norte_norteFic":4913.431,"norteFic_nordeste":280.621582}}