{"Data":"2025-11-18T11:13:00-03:00","sudesteECentroOeste":{"geracao":{"total":46483.043,"hidraulica":13282.0713,"termica":6112.90234,"eolica":14.9140625,"nuclear":2012.183,"solar":19574.1875,"itaipu50HzBrasil":1099.37,"itaipu60Hz":4387.41357},"cargaVerificada":52419.86,"importacao":5936.818,"exportacao":0.0},"sul":{"geracao":{"total":16653.207,"hidraulica":9805.28,"termica":1110.9021,"eolica":545.2346,"nuclear":0.0,"solar":5191.79},"cargaVerificada":15876.3428,"importacao":0.2599012,"exportacao":777.124146},"nordeste":{"geracao":{"total":20442.6152,"hidraulica":2335.22754,"termica":2769.65137,"eolica":3550.17749,"nuclear":0.0,"solar":11787.5586},"cargaVerificada":14452.9473,"importacao":0.0,"exportacao":5989.456},"norte":{"geracao":{"total":8782.908,"hidraulica":3285.241,"termica":3140.76147,"eolica":181.396378,"nuclear":0.0,"solar":2175.50977},"cargaVerificada":9612.671,"importacao":829.7623,"exportacao":0.0},"internacional":{"argentina":-0.004537356,"paraguai":0.0,"uruguai":-0.227166668},"intercambio":{"internacional_sul":0.2599012,"sul_sudeste":777.124146,"sudeste_nordeste":-2309.69165,"sudeste_norteFic":-2850.002,"norte_norteFic":-829.7623,"norteFic_nordeste":-3679.76416}}