{"Data":"2024-05-16T05:54:00-03:00","sudesteECentroOeste":{"geracao":{"total":25919.582,"hidraulica":17155.2422,"termica":4059.12573,"eolica":3.0,"nuclear":1356.96216,"solar":15.8008728,"itaipu50HzBrasil":1146.66,"itaipu60Hz":2182.79175},"cargaVerificada":39669.07,"importacao":14369.0557,"exportacao":619.568359},"sul":{"geracao":{"total":9971.88,"hidraulica":8917.739,"termica":839.543335,"eolica":214.597382,"nuclear":0.0,"solar":0.0},"cargaVerificada":10591.3818,"importacao":619.568359,"exportacao":0.06648591},"nordeste":{"geracao":{"total":19672.6719,"hidraulica":2468.89,"termica":282.208038,"eolica":16588.9727,"nuclear":0.0,"solar":332.600525},"cargaVerificada":12047.9658,"importacao":0.0,"exportacao":7619.834},"norte":{"geracao":{"total":14057.8584,"hidraulica":12906.0928,"termica":1133.21545,"eolica":0.265662074,"nuclear":0.0,"solar":18.2844448},"cargaVerificada":7308.636,"importacao":0.0,"exportacao":6749.222},"internacional":{"argentina":-0.0006778936,"paraguai":0.0,"uruguai":0.09899999},"intercambio":{"internacional_sul":-0.06648591,"sul_sudeste":-619.568359,"sudeste_nordeste":-1196.06189,"sudeste_norteFic":-13172.9941,"norte_norteFic":6749.222,"norteFic_nordeste":-6423.772}}