{"Data":"2026-05-30T07:59:00-03:00","sudesteECentroOeste":{"geracao":{"total":34979.1,"hidraulica":17037.2637,"termica":4703.48438,"eolica":76.81927,"nuclear":2006.95764,"solar":6936.06738,"itaipu50HzBrasil":754.24,"itaipu60Hz":3464.27075},"cargaVerificada":39837.5742,"importacao":12182.7852,"exportacao":7324.31445},"sul":{"geracao":{"total":5655.00537,"hidraulica":2927.41846,"termica":1785.58679,"eolica":302.919922,"nuclear":0.0,"solar":639.08},"cargaVerificada":11914.6982,"importacao":7324.31445,"exportacao":1064.62122},"nordeste":{"geracao":{"total":22302.55,"hidraulica":1976.77234,"termica":292.0003,"eolica":14488.6172,"nuclear":0.0,"solar":5545.16064},"cargaVerificada":12543.1689,"importacao":0.0,"exportacao":9758.25},"norte":{"geracao":{"total":10271.5127,"hidraulica":6565.2207,"termica":2756.25244,"eolica":233.545837,"nuclear":0.0,"solar":716.493347},"cargaVerificada":7846.97656,"importacao":0.0,"exportacao":2424.53564},"internacional":{"argentina":1064.75745,"paraguai":0.0,"uruguai":-0.127833337},"intercambio":{"internacional_sul":-1064.62122,"sul_sudeste":-7324.31445,"sudeste_nordeste":-5865.686,"sudeste_norteFic":-6317.09961,"norte_norteFic":2424.53564,"norteFic_nordeste":-3892.564}}