{"Data":"2026-01-13T21:05:00-03:00","sudesteECentroOeste":{"geracao":{"total":43116.98,"hidraulica":31128.9141,"termica":2635.78442,"eolica":246.015884,"nuclear":1645.63977,"solar":8.15758,"itaipu50HzBrasil":1850.46936,"itaipu60Hz":5602.0},"cargaVerificada":55040.6,"importacao":13651.3467,"exportacao":1727.7262},"sul":{"geracao":{"total":16236.18,"hidraulica":15173.5166,"termica":914.698364,"eolica":146.964355,"nuclear":0.0,"solar":1.0},"cargaVerificada":17964.3789,"importacao":1728.19958,"exportacao":0.0},"nordeste":{"geracao":{"total":22849.1289,"hidraulica":5058.69336,"termica":1711.07825,"eolica":16075.2754,"nuclear":0.0,"solar":4.08204651},"cargaVerificada":16181.8945,"importacao":0.0,"exportacao":6667.44141},"norte":{"geracao":{"total":15486.3076,"hidraulica":12178.0049,"termica":2914.50171,"eolica":393.8012,"nuclear":0.0,"solar":0.0},"cargaVerificada":8502.402,"importacao":0.0,"exportacao":6983.90527},"internacional":{"argentina":-0.00107447337,"paraguai":0.0,"uruguai":-0.468999982},"intercambio":{"internacional_sul":0.4734078,"sul_sudeste":-1727.7262,"sudeste_nordeste":-5612.87256,"sudeste_norteFic":-8038.474,"norte_norteFic":6983.90527,"norteFic_nordeste":-1054.56885}}