{"Data":"2024-09-11T02:38:00-03:00","sudesteECentroOeste":{"geracao":{"total":33406.6133,"hidraulica":19729.6,"termica":7011.44434,"eolica":6.0,"nuclear":2005.394,"solar":4.904808,"itaipu50HzBrasil":1434.51013,"itaipu60Hz":3214.76074},"cargaVerificada":39977.84,"importacao":8506.303,"exportacao":1935.07568},"sul":{"geracao":{"total":8977.453,"hidraulica":7283.33057,"termica":1185.81091,"eolica":507.312042,"nuclear":0.0,"solar":1.0},"cargaVerificada":10912.0859,"importacao":1935.07568,"exportacao":0.442846715},"nordeste":{"geracao":{"total":23664.2,"hidraulica":2612.75073,"termica":985.9136,"eolica":20065.3223,"nuclear":0.0,"solar":0.2130259},"cargaVerificada":12682.8594,"importacao":0.0,"exportacao":10981.3945},"norte":{"geracao":{"total":6079.49268,"hidraulica":2526.062,"termica":3158.37524,"eolica":395.0555,"nuclear":0.0,"solar":0.0},"cargaVerificada":8554.585,"importacao":2475.09229,"exportacao":0.0},"internacional":{"argentina":0.005083892,"paraguai":0.0,"uruguai":0.401},"intercambio":{"internacional_sul":-0.442846715,"sul_sudeste":-1935.07568,"sudeste_nordeste":-1588.74463,"sudeste_norteFic":-6917.55762,"norte_norteFic":-2475.09229,"norteFic_nordeste":-9392.65}}