{"Data":"2024-09-11T23:14:00-03:00","sudesteECentroOeste":{"geracao":{"total":40270.6328,"hidraulica":24635.6328,"termica":9175.588,"eolica":7.0,"nuclear":2004.80249,"solar":4.584107,"itaipu50HzBrasil":1232.11,"itaipu60Hz":3210.91431},"cargaVerificada":48837.64,"importacao":8567.008,"exportacao":0.0},"sul":{"geracao":{"total":13911.12,"hidraulica":12263.7588,"termica":827.625366,"eolica":818.735535,"nuclear":0.0,"solar":1.0},"cargaVerificada":13943.9814,"importacao":311.18512,"exportacao":278.3238},"nordeste":{"geracao":{"total":24785.625,"hidraulica":4711.86865,"termica":1293.277,"eolica":18781.1563,"nuclear":0.0,"solar":-0.6769453},"cargaVerificada":13677.1,"importacao":0.0,"exportacao":11110.6377},"norte":{"geracao":{"total":6511.53955,"hidraulica":3067.0708,"termica":3043.811,"eolica":400.6576,"nuclear":0.0,"solar":0.0},"cargaVerificada":9333.494,"importacao":2821.95459,"exportacao":0.0},"internacional":{"argentina":-0.00260278978,"paraguai":0.0,"uruguai":-312.4257},"intercambio":{"internacional_sul":311.18512,"sul_sudeste":278.3238,"sudeste_nordeste":-1619.49731,"sudeste_norteFic":-6669.18652,"norte_norteFic":-2821.95459,"norteFic_nordeste":-9491.141}}