{"Data":"2024-05-31T12:18:00-03:00","sudesteECentroOeste":{"geracao":{"total":34376.01,"hidraulica":13481.64,"termica":4627.232,"eolica":3.0,"nuclear":2001.62158,"solar":11124.1328,"itaipu50HzBrasil":1120.65991,"itaipu60Hz":2017.72559},"cargaVerificada":39756.3164,"importacao":7715.43359,"exportacao":2335.129},"sul":{"geracao":{"total":10322.93,"hidraulica":5931.937,"termica":755.0428,"eolica":110.901283,"nuclear":0.0,"solar":3525.04858},"cargaVerificada":11909.2852,"importacao":2335.129,"exportacao":748.7735},"nordeste":{"geracao":{"total":17961.6133,"hidraulica":2407.97363,"termica":271.905884,"eolica":8347.208,"nuclear":0.0,"solar":6934.52637},"cargaVerificada":12484.9707,"importacao":0.0,"exportacao":5473.968},"norte":{"geracao":{"total":9698.11,"hidraulica":6784.517,"termica":1597.05078,"eolica":102.000137,"nuclear":0.0,"solar":1214.54224},"cargaVerificada":7456.64453,"importacao":0.0,"exportacao":2241.46582},"internacional":{"argentina":749.2524,"paraguai":0.0,"uruguai":-0.581241667},"intercambio":{"internacional_sul":-748.7735,"sul_sudeste":-2335.129,"sudeste_nordeste":-985.089661,"sudeste_norteFic":-6730.34375,"norte_norteFic":2241.46582,"norteFic_nordeste":-4488.878}}