{"Data":"2025-02-09T05:39:00-03:00","sudesteECentroOeste":{"geracao":{"total":40448.6563,"hidraulica":28650.293,"termica":3225.8374,"eolica":12.0,"nuclear":1983.46912,"solar":135.1066,"itaipu50HzBrasil":2224.68018,"itaipu60Hz":4217.26855},"cargaVerificada":40184.3633,"importacao":7692.88965,"exportacao":7957.181},"sul":{"geracao":{"total":5790.078,"hidraulica":4745.50049,"termica":781.761841,"eolica":236.362854,"nuclear":0.0,"solar":26.4527779},"cargaVerificada":12027.2686,"importacao":7957.181,"exportacao":1719.9906},"nordeste":{"geracao":{"total":15657.3213,"hidraulica":2799.098,"termica":407.432343,"eolica":12283.9336,"nuclear":0.0,"solar":166.857758},"cargaVerificada":11863.792,"importacao":0.0,"exportacao":3793.22583},"norte":{"geracao":{"total":11076.7344,"hidraulica":9974.419,"termica":1006.84052,"eolica":92.83042,"nuclear":0.0,"solar":2.64444447},"cargaVerificada":7177.071,"importacao":0.0,"exportacao":3899.66357},"internacional":{"argentina":1467.89331,"paraguai":0.0,"uruguai":252.119736},"intercambio":{"internacional_sul":-1719.9906,"sul_sudeste":-7957.181,"sudeste_nordeste":-2590.1604,"sudeste_norteFic":-5102.729,"norte_norteFic":3899.66357,"norteFic_nordeste":-1203.06543}}