{"Data":"2025-02-09T17:14:00-03:00","sudesteECentroOeste":{"geracao":{"total":42474.9375,"hidraulica":26631.5273,"termica":2755.96045,"eolica":18.0,"nuclear":1982.453,"solar":4411.99951,"itaipu50HzBrasil":2221.71,"itaipu60Hz":4453.289},"cargaVerificada":45713.48,"importacao":8191.02441,"exportacao":4952.4834},"sul":{"geracao":{"total":11299.5586,"hidraulica":8289.776,"termica":826.8071,"eolica":472.470245,"nuclear":0.0,"solar":1710.505},"cargaVerificada":14784.6914,"importacao":4952.4834,"exportacao":1467.351},"nordeste":{"geracao":{"total":15662.3154,"hidraulica":3863.30176,"termica":423.1187,"eolica":9999.274,"nuclear":0.0,"solar":1376.62012},"cargaVerificada":11841.3135,"importacao":0.0,"exportacao":3821.80444},"norte":{"geracao":{"total":11248.3037,"hidraulica":9997.198,"termica":916.5295,"eolica":127.379433,"nuclear":0.0,"solar":207.196671},"cargaVerificada":6879.0835,"importacao":0.0,"exportacao":4369.22},"internacional":{"argentina":1468.01563,"paraguai":0.0,"uruguai":-0.626633346},"intercambio":{"internacional_sul":-1467.351,"sul_sudeste":-4952.4834,"sudeste_nordeste":-2889.84155,"sudeste_norteFic":-5301.183,"norte_norteFic":4369.22,"norteFic_nordeste":-931.9629}}