{"Data":"2026-07-09T15:07:00-03:00","sudesteECentroOeste":{"geracao":{"total":42896.1055,"hidraulica":14378.1143,"termica":6772.107,"eolica":3.27278638,"nuclear":2009.5874,"solar":14921.22,"itaipu50HzBrasil":1.19,"itaipu60Hz":4810.61426},"cargaVerificada":42875.3555,"importacao":4775.73828,"exportacao":4796.48828},"sul":{"geracao":{"total":10807.6621,"hidraulica":6197.17041,"termica":1534.01807,"eolica":85.66403,"nuclear":0.0,"solar":2990.80981},"cargaVerificada":14506.0771,"importacao":4796.48828,"exportacao":1098.07349},"nordeste":{"geracao":{"total":20941.05,"hidraulica":3736.63818,"termica":211.435608,"eolica":8146.559,"nuclear":0.0,"solar":8846.417},"cargaVerificada":13891.0576,"importacao":0.0,"exportacao":7051.43945},"norte":{"geracao":{"total":7070.567,"hidraulica":3377.39258,"termica":1628.19885,"eolica":375.2106,"nuclear":0.0,"solar":1689.76489},"cargaVerificada":9346.268,"importacao":2275.70068,"exportacao":0.0},"internacional":{"argentina":1098.869,"paraguai":0.0,"uruguai":-0.7568333},"intercambio":{"internacional_sul":-1098.07349,"sul_sudeste":-4796.48828,"sudeste_nordeste":-3244.85278,"sudeste_norteFic":-1530.88562,"norte_norteFic":-2275.70068,"norteFic_nordeste":-3806.58643}}