{"Data":"2026-04-14T11:42:00-03:00","sudesteECentroOeste":{"geracao":{"total":45877.71,"hidraulica":17928.3535,"termica":2240.182,"eolica":75.53125,"nuclear":1994.31128,"solar":18917.2676,"itaipu50HzBrasil":601.5,"itaipu60Hz":4120.56641},"cargaVerificada":47512.8828,"importacao":8672.855,"exportacao":7037.68457},"sul":{"geracao":{"total":9047.161,"hidraulica":3254.4978,"termica":318.6478,"eolica":829.4064,"nuclear":0.0,"solar":4644.609},"cargaVerificada":16084.9893,"importacao":7037.82861,"exportacao":0.0},"nordeste":{"geracao":{"total":20355.4238,"hidraulica":2090.12622,"termica":830.210938,"eolica":7543.81738,"nuclear":0.0,"solar":9891.27},"cargaVerificada":13649.7656,"importacao":0.0,"exportacao":6705.647},"norte":{"geracao":{"total":9979.951,"hidraulica":7131.776,"termica":929.792847,"eolica":33.05809,"nuclear":0.0,"solar":1885.32434},"cargaVerificada":8012.74268,"importacao":0.0,"exportacao":1967.2085},"internacional":{"argentina":0.004071199,"paraguai":0.0,"uruguai":-0.147166684},"intercambio":{"internacional_sul":0.143829823,"sul_sudeste":-7037.68457,"sudeste_nordeste":-3462.65527,"sudeste_norteFic":-5210.2,"norte_norteFic":1967.2085,"norteFic_nordeste":-3242.9917}}