{"Data":"2026-01-21T00:04:00-03:00","sudesteECentroOeste":{"geracao":{"total":36700.9336,"hidraulica":27343.9473,"termica":2543.8396,"eolica":56.8181,"nuclear":468.096344,"solar":8.872824,"itaipu50HzBrasil":1904.96094,"itaipu60Hz":4374.39746},"cargaVerificada":42304.43,"importacao":7169.0083,"exportacao":1565.51123},"sul":{"geracao":{"total":12544.3721,"hidraulica":10850.8555,"termica":807.6138,"eolica":884.9032,"nuclear":0.0,"solar":1.0},"cargaVerificada":14109.8525,"importacao":1565.51123,"exportacao":0.0310922023},"nordeste":{"geracao":{"total":14811.3174,"hidraulica":3342.21265,"termica":2777.75122,"eolica":8688.876,"nuclear":0.0,"solar":2.477181},"cargaVerificada":15209.9443,"importacao":2609.05664,"exportacao":2210.60156},"norte":{"geracao":{"total":16272.2266,"hidraulica":12731.1436,"termica":3350.48535,"eolica":190.597183,"nuclear":0.0,"solar":0.0},"cargaVerificada":8704.763,"importacao":0.0,"exportacao":7567.46338},"internacional":{"argentina":-0.00107447337,"paraguai":0.0,"uruguai":0.0321666747},"intercambio":{"internacional_sul":-0.0310922023,"sul_sudeste":-1565.51123,"sudeste_nordeste":-2210.60156,"sudeste_norteFic":-4958.40674,"norte_norteFic":7567.46338,"norteFic_nordeste":2609.05664}}