{"Data":"2024-08-08T21:11:00-03:00","sudesteECentroOeste":{"geracao":{"total":36935.7148,"hidraulica":20612.9316,"termica":8131.60938,"eolica":7.0,"nuclear":2003.15674,"solar":7.273202,"itaipu50HzBrasil":1962.42993,"itaipu60Hz":4211.315},"cargaVerificada":49746.77,"importacao":12811.0547,"exportacao":0.0},"sul":{"geracao":{"total":17399.541,"hidraulica":15395.2178,"termica":1139.96716,"eolica":863.356934,"nuclear":0.0,"solar":1.0},"cargaVerificada":15038.8174,"importacao":0.0,"exportacao":2360.72363},"nordeste":{"geracao":{"total":24424.9844,"hidraulica":6002.26367,"termica":1061.58362,"eolica":17360.6875,"nuclear":0.0,"solar":0.449232846},"cargaVerificada":13813.8389,"importacao":0.0,"exportacao":10611.2461},"norte":{"geracao":{"total":8381.675,"hidraulica":5568.67773,"termica":2493.48828,"eolica":319.509033,"nuclear":0.0,"solar":0.0},"cargaVerificada":8542.465,"importacao":160.790039,"exportacao":0.0},"internacional":{"argentina":0.00512777828,"paraguai":0.0,"uruguai":0.09313332},"intercambio":{"internacional_sul":-0.124945484,"sul_sudeste":2360.59863,"sudeste_nordeste":-1643.22375,"sudeste_norteFic":-8807.232,"norte_norteFic":-160.790039,"norteFic_nordeste":-8968.022}}