{"Data":"2025-01-04T10:15:00-03:00","sudesteECentroOeste":{"geracao":{"total":38763.38,"hidraulica":17091.373,"termica":2345.5415,"eolica":4.0,"nuclear":2004.14941,"solar":13390.8027,"itaipu50HzBrasil":928.73,"itaipu60Hz":2998.78345},"cargaVerificada":43081.0273,"importacao":5676.363,"exportacao":1358.71558},"sul":{"geracao":{"total":11712.0566,"hidraulica":5399.198,"termica":70.593956,"eolica":1098.31287,"nuclear":0.0,"solar":5143.951},"cargaVerificada":13071.7744,"importacao":1359.71826,"exportacao":0.0},"nordeste":{"geracao":{"total":19061.5215,"hidraulica":2162.95239,"termica":559.3505,"eolica":6173.1543,"nuclear":0.0,"solar":10166.0645},"cargaVerificada":12709.1523,"importacao":0.0,"exportacao":6351.31641},"norte":{"geracao":{"total":6223.595,"hidraulica":3516.74683,"termica":1265.54565,"eolica":247.960861,"nuclear":0.0,"solar":1193.34167},"cargaVerificada":6898.549,"importacao":674.9538,"exportacao":0.0},"internacional":{"argentina":-0.00304704579,"paraguai":0.0,"uruguai":-0.988},"intercambio":{"internacional_sul":1.00265527,"sul_sudeste":-1358.71558,"sudeste_nordeste":-3254.8606,"sudeste_norteFic":-2421.5022,"norte_norteFic":-674.9538,"norteFic_nordeste":-3096.456}}