{"Data":"2025-06-22T11:30:00-03:00","sudesteECentroOeste":{"geracao":{"total":35762.2227,"hidraulica":13306.7744,"termica":3884.56128,"eolica":18.86914,"nuclear":1362.68433,"solar":13163.5117,"itaipu50HzBrasil":751.473938,"itaipu60Hz":3274.34839},"cargaVerificada":36519.5938,"importacao":3084.85986,"exportacao":2327.48926},"sul":{"geracao":{"total":8986.739,"hidraulica":5189.853,"termica":1413.60925,"eolica":48.01614,"nuclear":0.0,"solar":2335.26123},"cargaVerificada":10402.7813,"importacao":2327.48926,"exportacao":911.447632},"nordeste":{"geracao":{"total":13310.2363,"hidraulica":2330.968,"termica":248.818085,"eolica":4717.472,"nuclear":0.0,"solar":6012.978},"cargaVerificada":9885.168,"importacao":0.0,"exportacao":3424.03149},"norte":{"geracao":{"total":6461.31738,"hidraulica":2957.29956,"termica":1644.32385,"eolica":132.337082,"nuclear":0.0,"solar":1727.35669},"cargaVerificada":6800.489,"importacao":339.17157,"exportacao":0.0},"internacional":{"argentina":912.3848,"paraguai":0.0,"uruguai":-0.707},"intercambio":{"internacional_sul":-911.447632,"sul_sudeste":-2327.48926,"sudeste_nordeste":-2041.39575,"sudeste_norteFic":-1043.46411,"norte_norteFic":-339.17157,"norteFic_nordeste":-1382.63574}}