{"Data":"2025-09-10T00:50:00-03:00","sudesteECentroOeste":{"geracao":{"total":30297.1719,"hidraulica":18240.6934,"termica":5670.675,"eolica":169.170441,"nuclear":2011.51416,"solar":4.82633162,"itaipu50HzBrasil":1188.03,"itaipu60Hz":3012.26367},"cargaVerificada":40946.5,"importacao":10649.3271,"exportacao":0.0},"sul":{"geracao":{"total":13372.3926,"hidraulica":11345.7588,"termica":1164.27344,"eolica":861.3606,"nuclear":0.0,"solar":1.0},"cargaVerificada":10582.1387,"importacao":0.3567797,"exportacao":2790.61084},"nordeste":{"geracao":{"total":24655.66,"hidraulica":2171.94629,"termica":1487.25549,"eolica":20994.1855,"nuclear":0.0,"solar":2.272883},"cargaVerificada":13696.1494,"importacao":0.0,"exportacao":10959.5254},"norte":{"geracao":{"total":6034.21729,"hidraulica":2387.16,"termica":3272.64258,"eolica":374.415,"nuclear":0.0,"solar":0.0},"cargaVerificada":9135.026,"importacao":3100.80884,"exportacao":0.0},"internacional":{"argentina":0.005662076,"paraguai":0.0,"uruguai":-0.3645},"intercambio":{"internacional_sul":0.3567797,"sul_sudeste":2790.61084,"sudeste_nordeste":-6291.8667,"sudeste_norteFic":-1566.84961,"norte_norteFic":-3100.80884,"norteFic_nordeste":-4667.658}}