{"Data":"2025-02-27T15:57:00-03:00","sudesteECentroOeste":{"geracao":{"total":51648.2734,"hidraulica":30263.54,"termica":2012.89844,"eolica":13.0,"nuclear":1976.97,"solar":10763.1348,"itaipu50HzBrasil":1919.68018,"itaipu60Hz":4699.05127},"cargaVerificada":59439.3242,"importacao":12616.48,"exportacao":4825.42969},"sul":{"geracao":{"total":16661.1445,"hidraulica":12532.1279,"termica":1005.85651,"eolica":775.709534,"nuclear":0.0,"solar":2347.45142},"cargaVerificada":20927.7656,"importacao":4825.42969,"exportacao":558.809448},"nordeste":{"geracao":{"total":17830.16,"hidraulica":2582.41455,"termica":415.908844,"eolica":9646.847,"nuclear":0.0,"solar":5184.99},"cargaVerificada":15216.8848,"importacao":375.993164,"exportacao":2989.93945},"norte":{"geracao":{"total":18289.959,"hidraulica":16108.5605,"termica":1274.78821,"eolica":110.69548,"nuclear":0.0,"solar":795.915039},"cargaVerificada":8287.425,"importacao":0.0,"exportacao":10002.5342},"internacional":{"argentina":559.2911,"paraguai":0.0,"uruguai":-0.5585},"intercambio":{"internacional_sul":-558.809448,"sul_sudeste":-4825.42969,"sudeste_nordeste":-2989.93945,"sudeste_norteFic":-9626.541,"norte_norteFic":10002.5342,"norteFic_nordeste":375.993164}}