{"Data":"2024-12-06T04:26:00-03:00","sudesteECentroOeste":{"geracao":{"total":34457.793,"hidraulica":22169.2617,"termica":5094.81641,"eolica":7.0,"nuclear":649.282654,"solar":4.377597,"itaipu50HzBrasil":1926.3,"itaipu60Hz":4606.754},"cargaVerificada":38946.0977,"importacao":6929.34473,"exportacao":2441.03931},"sul":{"geracao":{"total":9852.604,"hidraulica":7648.816,"termica":1311.23291,"eolica":891.5551,"nuclear":0.0,"solar":1.0},"cargaVerificada":12294.2656,"importacao":2441.66162,"exportacao":0.0},"nordeste":{"geracao":{"total":21868.72,"hidraulica":3627.783,"termica":1104.307,"eolica":17138.37,"nuclear":0.0,"solar":-1.73840654},"cargaVerificada":13179.0918,"importacao":0.0,"exportacao":8689.438},"norte":{"geracao":{"total":5870.12451,"hidraulica":3026.837,"termica":2457.9917,"eolica":385.295837,"nuclear":0.0,"solar":0.0},"cargaVerificada":7630.21826,"importacao":1760.09375,"exportacao":0.0},"internacional":{"argentina":-0.00328328181,"paraguai":0.0,"uruguai":-0.6404333},"intercambio":{"internacional_sul":0.6223065,"sul_sudeste":-2441.03931,"sudeste_nordeste":-5898.111,"sudeste_norteFic":-1031.23376,"norte_norteFic":-1760.09375,"norteFic_nordeste":-2791.32764}}