{"Data":"2025-10-19T07:05:00-03:00","sudesteECentroOeste":{"geracao":{"total":28158.707,"hidraulica":10724.1592,"termica":6229.97,"eolica":13.3369789,"nuclear":2006.8678,"solar":4952.06641,"itaipu50HzBrasil":984.589966,"itaipu60Hz":3247.71558},"cargaVerificada":34648.9844,"importacao":6490.27832,"exportacao":0.0},"sul":{"geracao":{"total":11401.3682,"hidraulica":8480.695,"termica":937.138,"eolica":239.970871,"nuclear":0.0,"solar":1743.56433},"cargaVerificada":8549.787,"importacao":0.3070349,"exportacao":2851.88843},"nordeste":{"geracao":{"total":18143.4414,"hidraulica":2122.163,"termica":2130.58447,"eolica":7708.082,"nuclear":0.0,"solar":6182.611},"cargaVerificada":11746.127,"importacao":0.0,"exportacao":6395.415},"norte":{"geracao":{"total":5298.48,"hidraulica":2059.96558,"termica":2424.77881,"eolica":202.973465,"nuclear":0.0,"solar":610.7623},"cargaVerificada":8055.506,"importacao":2757.02563,"exportacao":0.0},"internacional":{"argentina":-0.0127394637,"paraguai":0.0,"uruguai":-0.2945},"intercambio":{"internacional_sul":0.3070349,"sul_sudeste":2851.88843,"sudeste_nordeste":-2592.98071,"sudeste_norteFic":-1045.409,"norte_norteFic":-2757.02563,"norteFic_nordeste":-3802.43457}}