{"Data":"2025-03-30T21:31:00-03:00","sudesteECentroOeste":{"geracao":{"total":42226.707,"hidraulica":30983.11,"termica":2963.29541,"eolica":2.0,"nuclear":1924.56189,"solar":9.413133,"itaipu50HzBrasil":2218.31,"itaipu60Hz":4126.01855},"cargaVerificada":48966.21,"importacao":14145.459,"exportacao":7405.957},"sul":{"geracao":{"total":7963.717,"hidraulica":5723.62354,"termica":967.922363,"eolica":1271.17078,"nuclear":0.0,"solar":1.0},"cargaVerificada":15370.25,"importacao":7406.533,"exportacao":0.0},"nordeste":{"geracao":{"total":21370.8418,"hidraulica":5700.948,"termica":329.946625,"eolica":15341.6895,"nuclear":0.0,"solar":-1.74217951},"cargaVerificada":14378.5313,"importacao":0.0,"exportacao":6992.63232},"norte":{"geracao":{"total":15256.9385,"hidraulica":14091.082,"termica":940.657349,"eolica":225.199,"nuclear":0.0,"solar":0.0},"cargaVerificada":8104.11133,"importacao":0.0,"exportacao":7152.827},"internacional":{"argentina":0.005789948,"paraguai":0.0,"uruguai":-0.468999982},"intercambio":{"internacional_sul":0.576374531,"sul_sudeste":-7405.957,"sudeste_nordeste":-6163.412,"sudeste_norteFic":-7982.04736,"norte_norteFic":7152.827,"norteFic_nordeste":-829.2202}}