{"Data":"2025-08-07T15:09:00-03:00","sudesteECentroOeste":{"geracao":{"total":40212.918,"hidraulica":15455.0205,"termica":6775.109,"eolica":8.506771,"nuclear":2013.32446,"solar":12676.1777,"itaipu50HzBrasil":992.019958,"itaipu60Hz":2292.761},"cargaVerificada":44809.08,"importacao":6102.92725,"exportacao":1506.76831},"sul":{"geracao":{"total":13484.5977,"hidraulica":8970.519,"termica":1676.43481,"eolica":906.115967,"nuclear":0.0,"solar":1931.52881},"cargaVerificada":13879.4619,"importacao":1506.76831,"exportacao":1111.90454},"nordeste":{"geracao":{"total":19840.793,"hidraulica":2203.22949,"termica":1198.37488,"eolica":7791.44,"nuclear":0.0,"solar":8647.749},"cargaVerificada":12941.34,"importacao":0.0,"exportacao":6901.65},"norte":{"geracao":{"total":8286.227,"hidraulica":3751.34375,"termica":3208.38965,"eolica":230.397736,"nuclear":0.0,"solar":1096.09546},"cargaVerificada":9084.949,"importacao":798.722656,"exportacao":0.0},"internacional":{"argentina":1112.9176,"paraguai":0.0,"uruguai":-0.7046667},"intercambio":{"internacional_sul":-1111.90454,"sul_sudeste":-1506.76831,"sudeste_nordeste":-3412.25879,"sudeste_norteFic":-2690.66846,"norte_norteFic":-798.722656,"norteFic_nordeste":-3489.391}}