{"Data":"2026-06-01T16:23:00-03:00","sudesteECentroOeste":{"geracao":{"total":41198.2773,"hidraulica":22517.1484,"termica":5117.87842,"eolica":9.763803,"nuclear":2007.49927,"solar":5840.622,"itaipu50HzBrasil":909.58,"itaipu60Hz":4795.785},"cargaVerificada":47005.5469,"importacao":9532.222,"exportacao":3724.95239},"sul":{"geracao":{"total":11951.9756,"hidraulica":8838.23,"termica":1822.40637,"eolica":374.5654,"nuclear":0.0,"solar":916.7733},"cargaVerificada":14659.7637,"importacao":3724.95239,"exportacao":1017.16431},"nordeste":{"geracao":{"total":14894.0234,"hidraulica":5069.77148,"termica":350.990082,"eolica":5529.599,"nuclear":0.0,"solar":3943.663},"cargaVerificada":14370.6455,"importacao":2074.61572,"exportacao":2599.08179},"norte":{"geracao":{"total":18029.5723,"hidraulica":14017.3789,"termica":3454.66626,"eolica":0.104987361,"nuclear":0.0,"solar":557.4222},"cargaVerificada":9021.816,"importacao":0.0,"exportacao":9007.756},"internacional":{"argentina":1017.68524,"paraguai":0.0,"uruguai":-0.567333341},"intercambio":{"internacional_sul":-1017.16431,"sul_sudeste":-3724.95239,"sudeste_nordeste":-2599.08179,"sudeste_norteFic":-6933.14,"norte_norteFic":9007.756,"norteFic_nordeste":2074.61572}}