{"Data":"2025-01-08T01:01:00-03:00","sudesteECentroOeste":{"geracao":{"total":42138.47,"hidraulica":31688.9824,"termica":2057.20142,"eolica":7.0,"nuclear":1352.32654,"solar":10.69945,"itaipu50HzBrasil":2018.82,"itaipu60Hz":5003.439},"cargaVerificada":42557.1055,"importacao":2296.06445,"exportacao":1877.42761},"sul":{"geracao":{"total":13990.8848,"hidraulica":13410.3555,"termica":35.7257271,"eolica":543.804,"nuclear":0.0,"solar":1.0},"cargaVerificada":13661.6094,"importacao":115.23317,"exportacao":444.509},"nordeste":{"geracao":{"total":9445.091,"hidraulica":3023.16235,"termica":421.348145,"eolica":6000.95361,"nuclear":0.0,"solar":-0.373125732},"cargaVerificada":14743.4463,"importacao":5298.64,"exportacao":0.0},"norte":{"geracao":{"total":13795.4785,"hidraulica":12110.1035,"termica":1487.19092,"eolica":198.184113,"nuclear":0.0,"solar":0.0},"cargaVerificada":7962.96826,"importacao":0.0,"exportacao":5832.51025},"internacional":{"argentina":445.1065,"paraguai":0.0,"uruguai":-0.597499967},"intercambio":{"internacional_sul":-444.509,"sul_sudeste":-115.23317,"sudeste_nordeste":1762.19446,"sudeste_norteFic":-2296.06445,"norte_norteFic":5832.51025,"norteFic_nordeste":3536.4458}}