{"Data":"2025-03-12T01:14:00-03:00","sudesteECentroOeste":{"geracao":{"total":37723.0156,"hidraulica":26953.9023,"termica":2543.24268,"eolica":5.0,"nuclear":1994.768,"solar":5.65357542,"itaipu50HzBrasil":2225.71021,"itaipu60Hz":3994.738},"cargaVerificada":45962.16,"importacao":14211.2129,"exportacao":5972.06738},"sul":{"geracao":{"total":7055.02051,"hidraulica":5665.29834,"termica":635.85,"eolica":752.872253,"nuclear":0.0,"solar":1.0},"cargaVerificada":13027.53,"importacao":5972.51,"exportacao":0.0},"nordeste":{"geracao":{"total":20820.9023,"hidraulica":3554.13965,"termica":381.8379,"eolica":16889.0449,"nuclear":0.0,"solar":-4.119194},"cargaVerificada":14648.9268,"importacao":0.0,"exportacao":6172.062},"norte":{"geracao":{"total":16002.13,"hidraulica":14915.9072,"termica":1032.89441,"eolica":53.3281746,"nuclear":0.0,"solar":0.0},"cargaVerificada":7962.97949,"importacao":0.0,"exportacao":8039.15039},"internacional":{"argentina":0.00838934351,"paraguai":0.0,"uruguai":-0.5135},"intercambio":{"internacional_sul":0.442288339,"sul_sudeste":-5972.06738,"sudeste_nordeste":-5710.29834,"sudeste_norteFic":-8500.914,"norte_norteFic":8039.15039,"norteFic_nordeste":-461.763672}}