{"Data":"2025-04-21T03:52:00-03:00","sudesteECentroOeste":{"geracao":{"total":31100.2773,"hidraulica":22361.6348,"termica":3044.65576,"eolica":4.0,"nuclear":1351.729,"solar":4.868373,"itaipu50HzBrasil":1218.02,"itaipu60Hz":3115.36938},"cargaVerificada":33962.38,"importacao":7982.51953,"exportacao":5120.418},"sul":{"geracao":{"total":3830.85913,"hidraulica":2128.67529,"termica":1221.35181,"eolica":480.8321,"nuclear":0.0,"solar":0.0},"cargaVerificada":8533.949,"importacao":4703.09033,"exportacao":0.0},"nordeste":{"geracao":{"total":9134.789,"hidraulica":3947.50073,"termica":282.340332,"eolica":4906.14258,"nuclear":0.0,"solar":-1.19479024},"cargaVerificada":12925.749,"importacao":3790.94946,"exportacao":0.0},"norte":{"geracao":{"total":19179.8,"hidraulica":17850.1934,"termica":1196.73877,"eolica":132.868774,"nuclear":0.0,"solar":0.0},"cargaVerificada":7824.154,"importacao":0.0,"exportacao":11355.6475},"internacional":{"argentina":-0.00667016068,"paraguai":0.0,"uruguai":-0.5453333},"intercambio":{"internacional_sul":0.493911356,"sul_sudeste":-4702.596,"sudeste_nordeste":417.8216,"sudeste_norteFic":-7982.51953,"norte_norteFic":11355.6475,"norteFic_nordeste":3373.128}}