{"Data":"2025-06-07T19:41:00-03:00","sudesteECentroOeste":{"geracao":{"total":39286.7344,"hidraulica":26868.5176,"termica":4799.19727,"eolica":6.0,"nuclear":1359.631,"solar":6.984485,"itaipu50HzBrasil":1493.19006,"itaipu60Hz":4753.216},"cargaVerificada":47636.3555,"importacao":14687.4707,"exportacao":6337.85156},"sul":{"geracao":{"total":8021.564,"hidraulica":6205.00244,"termica":1591.10876,"eolica":224.452759,"nuclear":0.0,"solar":1.0},"cargaVerificada":13732.6523,"importacao":6337.85156,"exportacao":626.762939},"nordeste":{"geracao":{"total":22679.293,"hidraulica":5730.033,"termica":325.7692,"eolica":16612.67,"nuclear":0.0,"solar":10.82},"cargaVerificada":14403.7119,"importacao":0.0,"exportacao":8273.556},"norte":{"geracao":{"total":14975.5879,"hidraulica":13002.9619,"termica":1801.60779,"eolica":169.084839,"nuclear":0.0,"solar":1.93333328},"cargaVerificada":8561.673,"importacao":0.0,"exportacao":6413.915},"internacional":{"argentina":627.8395,"paraguai":0.0,"uruguai":-1.10483325},"intercambio":{"internacional_sul":-626.762939,"sul_sudeste":-6337.85156,"sudeste_nordeste":-6603.518,"sudeste_norteFic":-8083.95264,"norte_norteFic":6413.915,"norteFic_nordeste":-1670.0376}}