{"Data":"2026-02-16T10:34:00-03:00","sudesteECentroOeste":{"geracao":{"total":42653.4258,"hidraulica":16317.2158,"termica":3395.76221,"eolica":136.446487,"nuclear":468.688171,"solar":18926.5156,"itaipu50HzBrasil":301.95,"itaipu60Hz":3106.84668},"cargaVerificada":47462.81,"importacao":9148.579,"exportacao":4339.19531},"sul":{"geracao":{"total":13152.86,"hidraulica":5934.089,"termica":1388.85437,"eolica":440.388428,"nuclear":0.0,"solar":5389.529},"cargaVerificada":17491.9316,"importacao":4339.19531,"exportacao":0.124382295},"nordeste":{"geracao":{"total":19540.9766,"hidraulica":1935.306,"termica":506.023071,"eolica":6520.38574,"nuclear":0.0,"solar":10579.2607},"cargaVerificada":10688.5781,"importacao":0.0,"exportacao":8851.391},"norte":{"geracao":{"total":7531.40234,"hidraulica":4735.71338,"termica":1248.67908,"eolica":39.69891,"nuclear":0.0,"solar":1507.311},"cargaVerificada":7234.214,"importacao":0.0,"exportacao":297.188538},"internacional":{"argentina":0.000321679661,"paraguai":0.0,"uruguai":0.123999991},"intercambio":{"internacional_sul":-0.124382295,"sul_sudeste":-4339.19531,"sudeste_nordeste":-4785.55029,"sudeste_norteFic":-4363.029,"norte_norteFic":297.188538,"norteFic_nordeste":-4065.84033}}