{"Data":"2024-09-05T02:12:00-03:00","sudesteECentroOeste":{"geracao":{"total":34211.8047,"hidraulica":19128.39,"termica":7732.24951,"eolica":6.0,"nuclear":2008.8822,"solar":4.19233847,"itaipu50HzBrasil":2118.80029,"itaipu60Hz":3213.2915},"cargaVerificada":39619.1172,"importacao":7418.1333,"exportacao":2010.82068},"sul":{"geracao":{"total":8603.942,"hidraulica":7330.90771,"termica":691.1834,"eolica":580.85144,"nuclear":0.0,"solar":1.0},"cargaVerificada":10505.0723,"importacao":2010.82068,"exportacao":109.690826},"nordeste":{"geracao":{"total":22563.7832,"hidraulica":2831.75244,"termica":357.656525,"eolica":19374.0781,"nuclear":0.0,"solar":0.296376824},"cargaVerificada":12449.5605,"importacao":0.0,"exportacao":10113.9707},"norte":{"geracao":{"total":5775.25049,"hidraulica":2459.771,"termica":2914.46387,"eolica":401.0156,"nuclear":0.0,"solar":0.0},"cargaVerificada":8471.088,"importacao":2695.8374,"exportacao":0.0},"internacional":{"argentina":108.733589,"paraguai":0.0,"uruguai":0.955666661},"intercambio":{"internacional_sul":-109.690826,"sul_sudeste":-2010.82068,"sudeste_nordeste":-1503.44885,"sudeste_norteFic":-5914.68457,"norte_norteFic":-2695.8374,"norteFic_nordeste":-8610.521}}