{"Data":"2024-11-25T16:27:00-03:00","sudesteECentroOeste":{"geracao":{"total":50997.0938,"hidraulica":31458.8164,"termica":4621.01074,"eolica":6.0,"nuclear":649.07,"solar":7564.05127,"itaipu50HzBrasil":2019.49,"itaipu60Hz":4678.65674},"cargaVerificada":49481.6953,"importacao":825.178162,"exportacao":2340.57813},"sul":{"geracao":{"total":17015.5059,"hidraulica":13315.4033,"termica":1376.7948,"eolica":370.6139,"nuclear":0.0,"solar":1952.69446},"cargaVerificada":18153.17,"importacao":1574.6438,"exportacao":436.980316},"nordeste":{"geracao":{"total":15723.6816,"hidraulica":3684.11426,"termica":535.9407,"eolica":9248.614,"nuclear":0.0,"solar":2255.013},"cargaVerificada":14629.834,"importacao":0.0,"exportacao":1094.71851},"norte":{"geracao":{"total":7746.34375,"hidraulica":5775.202,"termica":1204.10657,"eolica":389.812836,"nuclear":0.0,"solar":377.222229},"cargaVerificada":8781.818,"importacao":1035.47461,"exportacao":0.0},"internacional":{"argentina":436.908752,"paraguai":0.0,"uruguai":0.104916684},"intercambio":{"internacional_sul":-436.980316,"sul_sudeste":-1574.6438,"sudeste_nordeste":-825.178162,"sudeste_norteFic":765.9342,"norte_norteFic":-1035.47461,"norteFic_nordeste":-269.5404}}