{"Data":"2024-08-10T07:00:00-03:00","sudesteECentroOeste":{"geracao":{"total":26879.43,"hidraulica":14552.3311,"termica":4984.856,"eolica":6.0,"nuclear":2004.08875,"solar":1361.93835,"itaipu50HzBrasil":1618.65015,"itaipu60Hz":2351.56543},"cargaVerificada":36338.1836,"importacao":9458.754,"exportacao":0.0},"sul":{"geracao":{"total":13853.1729,"hidraulica":11666.8242,"termica":1186.87085,"eolica":880.125366,"nuclear":0.0,"solar":119.352783},"cargaVerificada":10631.2373,"importacao":0.0,"exportacao":3221.93555},"nordeste":{"geracao":{"total":19860.5918,"hidraulica":2361.3606,"termica":727.6573,"eolica":11812.29,"nuclear":0.0,"solar":4959.284},"cargaVerificada":11209.415,"importacao":0.0,"exportacao":8656.037},"norte":{"geracao":{"total":6226.668,"hidraulica":3022.3208,"termica":2815.31323,"eolica":154.434982,"nuclear":0.0,"solar":234.598892},"cargaVerificada":7299.52148,"importacao":1072.85352,"exportacao":0.0},"internacional":{"argentina":1346.36523,"paraguai":0.0,"uruguai":-0.06050001},"intercambio":{"internacional_sul":-1346.3656,"sul_sudeste":1875.57,"sudeste_nordeste":-1245.351,"sudeste_norteFic":-6337.833,"norte_norteFic":-1072.85352,"norteFic_nordeste":-7410.68652}}