{"Data":"2024-12-04T12:42:00-03:00","sudesteECentroOeste":{"geracao":{"total":47407.5938,"hidraulica":20751.375,"termica":5762.58447,"eolica":7.0,"nuclear":647.4,"solar":12853.6406,"itaipu50HzBrasil":2928.52979,"itaipu60Hz":4457.0625},"cargaVerificada":47764.2773,"importacao":4934.65674,"exportacao":4577.97168},"sul":{"geracao":{"total":9797.358,"hidraulica":4558.29443,"termica":1335.14111,"eolica":184.065033,"nuclear":0.0,"solar":3719.858},"cargaVerificada":14376.1855,"importacao":4578.827,"exportacao":0.0},"nordeste":{"geracao":{"total":19221.29,"hidraulica":3350.994,"termica":1499.98157,"eolica":5257.74268,"nuclear":0.0,"solar":9112.57},"cargaVerificada":14128.7031,"importacao":0.0,"exportacao":5092.81348},"norte":{"geracao":{"total":7959.90137,"hidraulica":3998.20142,"termica":2564.80835,"eolica":211.6561,"nuclear":0.0,"solar":1185.2356},"cargaVerificada":8118.058,"importacao":158.156647,"exportacao":0.0},"internacional":{"argentina":-0.00211076438,"paraguai":0.0,"uruguai":-0.8525},"intercambio":{"internacional_sul":0.8554327,"sul_sudeste":-4577.97168,"sudeste_nordeste":-2812.7793,"sudeste_norteFic":-2121.87744,"norte_norteFic":-158.156647,"norteFic_nordeste":-2280.03418}}