{"Data":"2026-03-10T20:02:00-03:00","sudesteECentroOeste":{"geracao":{"total":48440.84,"hidraulica":37577.8477,"termica":3715.204,"eolica":137.4737,"nuclear":468.490662,"solar":9.988823,"itaipu50HzBrasil":1491.45,"itaipu60Hz":5040.38672},"cargaVerificada":54091.3125,"importacao":13096.1172,"exportacao":7445.64648},"sul":{"geracao":{"total":9860.142,"hidraulica":7763.58936,"termica":1095.01,"eolica":1000.54218,"nuclear":0.0,"solar":1.0},"cargaVerificada":17805.875,"importacao":7945.7334,"exportacao":0.0},"nordeste":{"geracao":{"total":19120.1777,"hidraulica":6315.767,"termica":523.246643,"eolica":12282.8467,"nuclear":0.0,"solar":-1.68352926},"cargaVerificada":15715.0908,"importacao":1574.123,"exportacao":4979.82227},"norte":{"geracao":{"total":18707.9688,"hidraulica":16444.0059,"termica":2045.99463,"eolica":217.969086,"nuclear":0.0,"solar":0.0},"cargaVerificada":9017.552,"importacao":0.0,"exportacao":9690.418},"internacional":{"argentina":-499.8091,"paraguai":0.0,"uruguai":-0.2661667},"intercambio":{"internacional_sul":500.087067,"sul_sudeste":-7445.64648,"sudeste_nordeste":-4979.82227,"sudeste_norteFic":-8116.295,"norte_norteFic":9690.418,"norteFic_nordeste":1574.123}}