{"Data":"2025-11-30T05:20:00-03:00","sudesteECentroOeste":{"geracao":{"total":30721.0254,"hidraulica":17461.6836,"termica":5757.41846,"eolica":9.1796875,"nuclear":2005.83472,"solar":414.1584,"itaipu50HzBrasil":1098.49,"itaipu60Hz":3974.26025},"cargaVerificada":37052.125,"importacao":6331.1,"exportacao":0.0},"sul":{"geracao":{"total":12719.8369,"hidraulica":10703.207,"termica":1419.36438,"eolica":526.8833,"nuclear":0.0,"solar":70.38222},"cargaVerificada":10675.4971,"importacao":0.0,"exportacao":2044.33984},"nordeste":{"geracao":{"total":16156.56,"hidraulica":2154.18481,"termica":1316.30835,"eolica":12257.6133,"nuclear":0.0,"solar":428.452942},"cargaVerificada":12758.4023,"importacao":0.0,"exportacao":3398.22974},"norte":{"geracao":{"total":9007.033,"hidraulica":5260.20361,"termica":3347.971,"eolica":396.958618,"nuclear":0.0,"solar":1.9},"cargaVerificada":8118.352,"importacao":0.0,"exportacao":888.681152},"internacional":{"argentina":-0.00401857,"paraguai":0.0,"uruguai":0.245500013},"intercambio":{"internacional_sul":-0.150938928,"sul_sudeste":2044.189,"sudeste_nordeste":-2610.82251,"sudeste_norteFic":-1676.08838,"norte_norteFic":888.681152,"norteFic_nordeste":-787.4072}}