{"Data":"2024-08-12T00:29:00-03:00","sudesteECentroOeste":{"geracao":{"total":24435.3477,"hidraulica":13208.47,"termica":5262.838,"eolica":7.0,"nuclear":2005.82263,"solar":8.147966,"itaipu50HzBrasil":1322.90991,"itaipu60Hz":2620.15918},"cargaVerificada":32496.2188,"importacao":8060.871,"exportacao":0.0},"sul":{"geracao":{"total":12429.459,"hidraulica":9575.3125,"termica":1106.90918,"eolica":1746.23743,"nuclear":0.0,"solar":1.0},"cargaVerificada":9656.093,"importacao":0.0,"exportacao":2773.36621},"nordeste":{"geracao":{"total":22117.02,"hidraulica":3133.21313,"termica":679.4126,"eolica":18303.19,"nuclear":0.0,"solar":1.20418286},"cargaVerificada":12486.8145,"importacao":0.0,"exportacao":9630.456},"norte":{"geracao":{"total":5724.35,"hidraulica":2594.22437,"termica":2743.57959,"eolica":386.546051,"nuclear":0.0,"solar":0.0},"cargaVerificada":8220.015,"importacao":2495.66455,"exportacao":0.0},"internacional":{"argentina":1847.20667,"paraguai":0.0,"uruguai":0.0789999962},"intercambio":{"internacional_sul":-1847.28564,"sul_sudeste":926.080566,"sudeste_nordeste":-1408.26233,"sudeste_norteFic":-5726.52832,"norte_norteFic":-2495.66455,"norteFic_nordeste":-8222.193}}