{"Data":"2025-06-21T11:00:00-03:00","sudesteECentroOeste":{"geracao":{"total":34595.3047,"hidraulica":13909.7432,"termica":4361.24365,"eolica":55.2470055,"nuclear":1364.40564,"solar":10902.8457,"itaipu50HzBrasil":903.329956,"itaipu60Hz":3098.49072},"cargaVerificada":39095.94,"importacao":7429.749,"exportacao":2929.11377},"sul":{"geracao":{"total":9819.306,"hidraulica":5109.631,"termica":1541.26147,"eolica":240.7684,"nuclear":0.0,"solar":2927.64453},"cargaVerificada":11401.4229,"importacao":2929.11377,"exportacao":1346.99609},"nordeste":{"geracao":{"total":19736.877,"hidraulica":2211.65063,"termica":246.245987,"eolica":10547.123,"nuclear":0.0,"solar":6731.85742},"cargaVerificada":11666.2334,"importacao":0.0,"exportacao":8085.56836},"norte":{"geracao":{"total":7190.905,"hidraulica":3134.74121,"termica":2014.78479,"eolica":274.270233,"nuclear":0.0,"solar":1767.1084},"cargaVerificada":7846.72363,"importacao":655.819,"exportacao":0.0},"internacional":{"argentina":1348.12732,"paraguai":0.0,"uruguai":-0.923666656},"intercambio":{"internacional_sul":-1346.99609,"sul_sudeste":-2929.11377,"sudeste_nordeste":-4350.643,"sudeste_norteFic":-3079.1062,"norte_norteFic":-655.819,"norteFic_nordeste":-3734.92529}}